MANIFEST.in
setup.py
grappelli_dynamic_navbar/__init__.py
grappelli_dynamic_navbar.egg-info/PKG-INFO
grappelli_dynamic_navbar.egg-info/SOURCES.txt
grappelli_dynamic_navbar.egg-info/dependency_links.txt
grappelli_dynamic_navbar.egg-info/requires.txt
grappelli_dynamic_navbar.egg-info/top_level.txt
grappelli_dynamic_navbar/templates/admin/base.html
grappelli_dynamic_navbar/templates/admin/index.html
grappelli_dynamic_navbar/templates/grappelli/navbar.html
grappelli_dynamic_navbar/templatetags/__init__.py
grappelli_dynamic_navbar/templatetags/grappelli_dynamic_navbar.py