Metadata-Version: 1.1
Name: grappelli-dynamic-navbar
Version: 0.1.1
Summary: Extensions for Grappelli Admin interface
Home-page: https://github.com/xangmuve/grappelli_dynamic_navbar
Author: Cesar Abel Ramirez
Author-email: cesarabel@johnmay.com.ni
License: BSD
Platform: UNKNOWN
Classifier: Development Status :: 5 - Production/Stable
Classifier: Intended Audience :: Developers
Classifier: License :: OSI Approved :: Apache Software License
Classifier: Programming Language :: Python
Classifier: Operating System :: OS Independent
Classifier: Topic :: Software Development :: Libraries
Classifier: Topic :: Utilities
Classifier: Environment :: Web Environment
Classifier: Framework :: Django
